ros_glint/__init__.py
ros_glint/_version.py
ros_glint/cmake_ordering.py
ros_glint/config.py
ros_glint/core.py
ros_glint/diff.py
ros_glint/glint_hook.py
ros_glint/main.py
ros_glint/python_types.py
ros_glint/terminal.py
ros_glint/util.py
ros_glint/data/cmake.ignore
ros_glint/data/cmake_patterns.ignore
ros_glint/data/package.ignore
ros_glint/data/package_patterns.ignore
ros_glint/data/rviz_class_defaults.yaml
ros_glint/data/rviz_generic_defaults.yaml
ros_glint/data/rviz_global_defaults.yaml
ros_glint/glinters/cmake.py
ros_glint/glinters/cmake_installs.py
ros_glint/glinters/cmake_pretty.py
ros_glint/glinters/cmake_sorting.py
ros_glint/glinters/misc.py
ros_glint/glinters/package_xml.py
ros_glint/glinters/plugins.py
ros_glint/glinters/python_setup.py
ros_glint/glinters/ros_interfaces.py
ros_glint/glinters/rviz_config.py
ros_glint-0.2.1.dist-info/METADATA
ros_glint-0.2.1.dist-info/WHEEL
ros_glint-0.2.1.dist-info/entry_points.txt
ros_glint-0.2.1.dist-info/licenses/LICENSE
ros_glint-0.2.1.dist-info/RECORD
