Metadata-Version: 2.3
Name: ros_glint
Version: 0.2.1
Summary: Pure Python library for linting ROS packages
Project-URL: Homepage, https://github.com/MetroRobots/ros_glint
Project-URL: Bug Tracker, https://github.com/MetroRobots/ros_glint/issues
Author-email: "David V. Lu!!" <davidvlu@gmail.com>
Maintainer-email: "David V. Lu!!" <davidvlu@gmail.com>
License-File: LICENSE
Classifier: Development Status :: 4 - Beta
Classifier: License :: OSI Approved :: BSD License
Classifier: Programming Language :: Python :: 3 :: Only
Classifier: Programming Language :: Python :: 3.8
Classifier: Topic :: Software Development
Requires-Python: >=3.8
Requires-Dist: betsy-ros
Requires-Dist: click
Requires-Dist: colorama
Requires-Dist: importlib-resources
Requires-Dist: pyyaml
Requires-Dist: ros-introspect
Provides-Extra: test
Requires-Dist: pooch; extra == 'test'
Requires-Dist: pytest; extra == 'test'
Requires-Dist: pytest-cov; extra == 'test'
